llama_index/llms/anthropic/__init__.py
llama_index/llms/anthropic/base.py
llama_index/llms/anthropic/py.typed
llama_index/llms/anthropic/utils.py
llama_index_llms_anthropic-0.10.7.dist-info/METADATA
llama_index_llms_anthropic-0.10.7.dist-info/WHEEL
llama_index_llms_anthropic-0.10.7.dist-info/licenses/LICENSE
llama_index_llms_anthropic-0.10.7.dist-info/RECORD
