Metadata-Version: 2.4
Name: llama-index-llms-anthropic
Version: 0.10.7
Summary: llama-index llms anthropic integration
Author-email: Your Name <you@example.com>
License-Expression: MIT
License-File: LICENSE
Requires-Python: <4.0,>=3.9
Requires-Dist: anthropic[bedrock,vertex]>=0.75.0
Requires-Dist: llama-index-core<0.15,>=0.14.5
